Workbook

Sheet Ringkasan
A1: RINGKASAN EKSEKUTIF PENGUJIAN BLACKBOX
A2: Sistem Manajemen Operasional & Pelaporan PT Signal Panca Utama
B4: Total Pengujian | C4: Valid (Lulus) | D4: Tidak Valid (Gagal) | E4: Blocked (Terhambat) | F4: Tingkat Kelulusan
B5: =C26 | C5: =D26 | D5: =E26 | E5: =F26 | F5: =G26
A7: 1. REKAPITULASI PENGUJIAN PER MODUL
A9: No | B9: Nama Modul Sistem | C9: Total Test Case | D9: Valid | E9: Tidak Valid | F9: Blocked | G9: % Kelulusan
A10: 1 | B10: Beranda | C10: =COUNTA('Beranda'!F5:F9) | D10: =COUNTIF('Beranda'!F5:F9, "Valid") | E10: =COUNTIF('Beranda'!F5:F9, "Tidak Valid") | F10: =COUNTIF('Beranda'!F5:F9, "Blocked") | G10: =IF(C10>0, D10/C10, 0)
A11: 2 | B11: Login | C11: =COUNTA('Login'!F5:F17) | D11: =COUNTIF('Login'!F5:F17, "Valid") | E11: =COUNTIF('Login'!F5:F17, "Tidak Valid") | F11: =COUNTIF('Login'!F5:F17, "Blocked") | G11: =IF(C11>0, D11/C11, 0)
A12: 3 | B12: Dashboard | C12: =COUNTA('Dashboard'!F5:F7) | D12: =COUNTIF('Dashboard'!F5:F7, "Valid") | E12: =COUNTIF('Dashboard'!F5:F7, "Tidak Valid") | F12: =COUNTIF('Dashboard'!F5:F7, "Blocked") | G12: =IF(C12>0, D12/C12, 0)
A13: 4 | B13: Tender_Administrasi | C13: =COUNTA('Tender_Administrasi'!F5:F9) | D13: =COUNTIF('Tender_Administrasi'!F5:F9, "Valid") | E13: =COUNTIF('Tender_Administrasi'!F5:F9, "Tidak Valid") | F13: =COUNTIF('Tender_Administrasi'!F5:F9, "Blocked") | G13: =IF(C13>0, D13/C13, 0)
A14: 5 | B14: Tender_RAB | C14: =COUNTA('Tender_RAB'!F5:F7) | D14: =COUNTIF('Tender_RAB'!F5:F7, "Valid") | E14: =COUNTIF('Tender_RAB'!F5:F7, "Tidak Valid") | F14: =COUNTIF('Tender_RAB'!F5:F7, "Blocked") | G14: =IF(C14>0, D14/C14, 0)
A15: 6 | B15: Tender_Proyek | C15: =COUNTA('Tender_Proyek'!F5:F7) | D15: =COUNTIF('Tender_Proyek'!F5:F7, "Valid") | E15: =COUNTIF('Tender_Proyek'!F5:F7, "Tidak Valid") | F15: =COUNTIF('Tender_Proyek'!F5:F7, "Blocked") | G15: =IF(C15>0, D15/C15, 0)
A16: 7 | B16: Klien_Kontrak | C16: =COUNTA('Klien_Kontrak'!F5:F8) | D16: =COUNTIF('Klien_Kontrak'!F5:F8, "Valid") | E16: =COUNTIF('Klien_Kontrak'!F5:F8, "Tidak Valid") | F16: =COUNTIF('Klien_Kontrak'!F5:F8, "Blocked") | G16: =IF(C16>0, D16/C16, 0)
A17: 8 | B17: Jasa_Pekerjaan | C17: =COUNTA('Jasa_Pekerjaan'!F5:F7) | D17: =COUNTIF('Jasa_Pekerjaan'!F5:F7, "Valid") | E17: =COUNTIF('Jasa_Pekerjaan'!F5:F7, "Tidak Valid") | F17: =COUNTIF('Jasa_Pekerjaan'!F5:F7, "Blocked") | G17: =IF(C17>0, D17/C17, 0)
A18: 9 | B18: Jasa_Operasional | C18: =COUNTA('Jasa_Operasional'!F5:F7) | D18: =COUNTIF('Jasa_Operasional'!F5:F7, "Valid") | E18: =COUNTIF('Jasa_Operasional'!F5:F7, "Tidak Valid") | F18: =COUNTIF('Jasa_Operasional'!F5:F7, "Blocked") | G18: =IF(C18>0, D18/C18, 0)
A19: 10 | B19: Supplier_Pengadaan | C19: =COUNTA('Supplier_Pengadaan'!F5:F8) | D19: =COUNTIF('Supplier_Pengadaan'!F5:F8, "Valid") | E19: =COUNTIF('Supplier_Pengadaan'!F5:F8, "Tidak Valid") | F19: =COUNTIF('Supplier_Pengadaan'!F5:F8, "Blocked") | G19: =IF(C19>0, D19/C19, 0)
A20: 11 | B20: Produk_Gudang | C20: =COUNTA('Produk_Gudang'!F5:F8) | D20: =COUNTIF('Produk_Gudang'!F5:F8, "Valid") | E20: =COUNTIF('Produk_Gudang'!F5:F8, "Tidak Valid") | F20: =COUNTIF('Produk_Gudang'!F5:F8, "Blocked") | G20: =IF(C20>0, D20/C20, 0)
A21: 12 | B21: Penjualan_Barang | C21: =COUNTA('Penjualan_Barang'!F5:F7) | D21: =COUNTIF('Penjualan_Barang'!F5:F7, "Valid") | E21: =COUNTIF('Penjualan_Barang'!F5:F7, "Tidak Valid") | F21: =COUNTIF('Penjualan_Barang'!F5:F7, "Blocked") | G21: =IF(C21>0, D21/C21, 0)
A22: 13 | B22: Dokumen_Komersial | C22: =COUNTA('Dokumen_Komersial'!F5:F6) | D22: =COUNTIF('Dokumen_Komersial'!F5:F6, "Valid") | E22: =COUNTIF('Dokumen_Komersial'!F5:F6, "Tidak Valid") | F22: =COUNTIF('Dokumen_Komersial'!F5:F6, "Blocked") | G22: =IF(C22>0, D22/C22, 0)
A23: 14 | B23: Keuangan_Finance | C23: =COUNTA('Keuangan_Finance'!F5:F7) | D23: =COUNTIF('Keuangan_Finance'!F5:F7, "Valid") | E23: =COUNTIF('Keuangan_Finance'!F5:F7, "Tidak Valid") | F23: =COUNTIF('Keuangan_Finance'!F5:F7, "Blocked") | G23: =IF(C23>0, D23/C23, 0)
A24: 15 | B24: Laporan_Ekspor | C24: =COUNTA('Laporan_Ekspor'!F5:F10) | D24: =COUNTIF('Laporan_Ekspor'!F5:F10, "Valid") | E24: =COUNTIF('Laporan_Ekspor'!F5:F10, "Tidak Valid") | F24: =COUNTIF('Laporan_Ekspor'!F5:F10, "Blocked") | G24: =IF(C24>0, D24/C24, 0)
A25: 16 | B25: Admin_Sistem | C25: =COUNTA('Admin_Sistem'!F5:F12) | D25: =COUNTIF('Admin_Sistem'!F5:F12, "Valid") | E25: =COUNTIF('Admin_Sistem'!F5:F12, "Tidak Valid") | F25: =COUNTIF('Admin_Sistem'!F5:F12, "Blocked") | G25: =IF(C25>0, D25/C25, 0)
B26: TOTAL KESELURUHAN | C26: =SUM(C10:C25) | D26: =SUM(D10:D25) | E26: =SUM(E10:E25) | F26: =SUM(F10:F25) | G26: =IF(C26>0, D26/C26, 0)
A29: 2. LINGKUNGAN PENGUJIAN (TEST ENVIRONMENT)
A30: Komponen Lingkungan | B30: Spesifikasi & Keterangan Pengujian
A31: Sistem Operasi (OS) | B31: Microsoft Windows 11 / Windows 10 x64
A32: Arsitektur Sistem | B32: Web Application berbasis MVC (Laravel 10.x, PHP 8.1.10)
A33: Basis Data (Database) | B33: MySQL 8.x (signal_niaga_jasa_tender), InnoDB, UTF8mb4
A34: Web / App Server | B34: Laravel Development Server (http://127.0.0.1:8000)
A35: Browser Pengujian | B35: Chromium v156 (Playwright Engine) & Microsoft Edge
A36: Perangkat Tool Pengujian | B36: Playwright Python v1.64.0, Requests v2.34.2, OpenPyXL v3.1.5, BeautifulSoup4
A37: Akun & Data Uji | B37: Dummy Seeder: owner@signalpanca.co.id, manager@signalpanca.co.id, admin@signalpanca.co.id
A38: Tingkat Risiko Keseluruhan | B38: RENDAH (LOW RISK) — 94.4% Fitur Berfungsi Sesuai Harapan

Sheet Beranda
A1: A. Pengujian Pada Halaman Beranda & Publik (Beranda)
A2: Sistem Manajemen Operasional & Pelaporan PT Signal Panca Utama — Format Baku Pengujian Blackbox
A4: No | B4: Skenario Pengujian | C4: Test Case | D4: Hasil yang Diharapkan | E4: Hasil Pengujian | F4: Kesimpulan
A5: 1 | B5: Sistem dapat memuat halaman Beranda publik versi desktop dengan lengkap | C5: Akses URL '/' dengan viewport desktop (1920x1080 px) | D5: Landing page termuat sempurna (HTTP 200) dengan struktur header, navbar, dan footer | E5: Sesuai Harapan (Status: 200, Durasi: 1.479s, Navbar: True, Footer: True) | F5: Valid
A6: 2 | B6: Sistem dapat menyesuaikan tata letak pada viewport layar mobile | C6: Ubah resolusi browser menjadi 375x812 px dan cek horizontal overflow | D6: Tampilan responsif, elemen menu tidak berantakan, tidak ada horizontal overflow | E6: Sesuai Harapan (scrollWidth: 375px, overflow: False) | F6: Valid
A7: 3 | B7: Sistem dapat menyesuaikan tata letak pada viewport layar tablet | C7: Ubah resolusi browser menjadi 768x1024 px dan periksa keterbacaan komponen | D7: Tampilan layout tablet proporsional dan tidak ada overflow horizontal | E7: Sesuai Harapan (scrollWidth: 768px) | F7: Valid
A8: 4 | B8: Sistem menyediakan tombol navigasi cepat menuju halaman autentikasi/login | C8: Verifikasi keberadaan tautan Masuk/Login di navbar landing page | D8: Terdapat tombol link Masuk yang mengarah tepat ke route '/login' | E8: Sesuai Harapan (Tombol ditemukan dengan href 'http://127.0.0.1:8000/login') | F8: Valid
A9: 5 | B9: Sistem menangani rute yang tidak valid dengan respons 404 Not Found | C9: Akses rute acak '/halaman-yang-pasti-tidak-ada-12345' | D9: Sistem merespons dengan HTTP status 404 Not Found tanpa crash server | E9: Sesuai Harapan (HTTP Status: 404) | F9: Valid

Sheet Login
A1: A. Pengujian Pada Autentikasi & Akun (Login)
A2: Sistem Manajemen Operasional & Pelaporan PT Signal Panca Utama — Format Baku Pengujian Blackbox
A4: No | B4: Skenario Pengujian | C4: Test Case | D4: Hasil yang Diharapkan | E4: Hasil Pengujian | F4: Kesimpulan
A5: 1 | B5: Sistem menampilkan form autentikasi lengkap dengan field input email, password, dan CAPTCHA | C5: Buka URL '/login' dan verifikasi seluruh kontrol input | D5: Halaman login menampilkan input email, password, kode visual CAPTCHA, dan tombol submit | E5: Sesuai Harapan (Email: True, Password: True, CAPTCHA: True) | F5: Valid
A6: 2 | B6: Sistem mengizinkan autentikasi role Admin dengan kredensial valid | C6: Input email 'admin@signalpanca.co.id', password valid, kode CAPTCHA tepat, submit form | D6: Otentikasi berhasil dan dialihkan otomatis (HTTP 302 -> 200) ke /dashboard | E6: Sesuai Harapan (Pengguna berhasil masuk ke dashboard dengan sesi role admin) | F6: Valid
A7: 3 | B7: Sistem mengizinkan autentikasi role Manager dengan kredensial valid | C7: Input email 'manager@signalpanca.co.id', password valid, kode CAPTCHA tepat, submit form | D7: Otentikasi berhasil dan dialihkan otomatis ke /dashboard dengan hak akses manager | E7: Sesuai Harapan (Pengguna berhasil masuk ke dashboard dengan sesi role manager) | F7: Valid
A8: 4 | B8: Sistem mengizinkan autentikasi role Owner dengan kredensial valid | C8: Input email 'owner@signalpanca.co.id', password valid, kode CAPTCHA tepat, submit form | D8: Otentikasi berhasil dan dialihkan otomatis ke /dashboard dengan hak akses owner | E8: Sesuai Harapan (Pengguna berhasil masuk ke dashboard dengan sesi role owner) | F8: Valid
A9: 5 | B9: Sistem menolak autentikasi bila password salah | C9: Isi email 'admin@signalpanca.co.id', password 'password_salah_123', CAPTCHA valid | D9: Sistem menolak login, tetap berada di /login, dan memberi pesan kesalahan | E9: Sesuai Harapan (Tetap berada pada URL http://127.0.0.1:8000/login) | F9: Valid
A10: 6 | B10: Sistem menolak autentikasi bila kode CAPTCHA salah | C10: Isi email dan password benar, namun isi CAPTCHA 'WRONG' | D10: Sistem memvalidasi kecocokan CAPTCHA dan menolak permintaan jika tidak sesuai | E10: Sesuai Harapan (Tetap di halaman login, URL: http://127.0.0.1:8000/login) | F10: Valid
A11: 7 | B11: Sistem menolak login jika email tidak terdaftar dalam database | C11: Isi email 'user_gaib@signalpanca.co.id', password 'password', submit form | D11: Sistem menolak login dan memberikan indikasi kredensial tidak cocok | E11: Sesuai Harapan (Otentikasi ditolak, URL: http://127.0.0.1:8000/login) | F11: Valid
A12: 8 | B12: Sistem memvalidasi field wajib saat formulir login dikirim dalam keadaan kosong | C12: Kosongkan seluruh field input dan klik tombol Masuk | D12: Sistem memicu validasi form required dan mencegah pengiriman data kosong | E12: Sesuai Harapan (Permintaan ditahan, URL: http://127.0.0.1:8000/login) | F12: Valid
A13: 9 | B13: Sistem memproteksi rute '/dashboard' dari akses pengguna guest tanpa autentikasi | C13: Kirim HTTP GET '/dashboard' tanpa menyertakan session cookie aktif | D13: Sistem mengembalikan status HTTP 302 Redirect mengarah ke '/login' | E13: Sesuai Harapan (Status: 302, Redirect ke: http://127.0.0.1:8000/login) | F13: Valid
A14: 10 | B14: Sistem menyediakan halaman lupa password untuk permohonan reset | C14: Akses URL '/forgot-password' | D14: Halaman lupa password terbuka (HTTP 200) dengan field email pemulihan | E14: Sesuai Harapan (Status: 200) | F14: Valid
A15: 11 | B15: Sistem dapat mengakhiri sesi autentikasi pengguna secara aman melalui rute logout | C15: Kirim POST '/logout' dengan menyertakan token CSRF sesi pengguna aktif | D15: Sesi dihancurkan, server mengarahkan kembali ke halaman '/login' | E15: Sesuai Harapan (Status HTTP: 302, Location: http://127.0.0.1:8000/login) | F15: Valid
A16: 12 | B16: Sistem mendukung login SSO OAuth dengan Google | C16: Akses rute '/auth/google/redirect' | D16: Dialihkan ke Google OAuth consent screen (Membutuhkan Google Client ID & Secret aktif) | E16: Status: 302. Belum terkonfigurasi pada environment lokal (.env kosong) | F16: Blocked
A17: 13 | B17: Sistem mendukung login SSO OAuth dengan LinkedIn | C17: Akses rute '/auth/linkedin/redirect' | D17: Dialihkan ke LinkedIn OAuth dialog (Membutuhkan LinkedIn Client ID & Secret aktif) | E17: Status: 302. Belum terkonfigurasi pada environment lokal (.env kosong) | F17: Blocked

Sheet Dashboard
A1: A. Pengujian Pada Halaman Dashboard Per Role (Dashboard)
A2: Sistem Manajemen Operasional & Pelaporan PT Signal Panca Utama — Format Baku Pengujian Blackbox
A4: No | B4: Skenario Pengujian | C4: Test Case | D4: Hasil yang Diharapkan | E4: Hasil Pengujian | F4: Kesimpulan
A5: 1 | B5: Sistem menampilkan ringkasan operasional pada dashboard role Admin | C5: Buka URL '/dashboard' pada sesi role Admin | D5: Halaman dashboard termuat sempurna (HTTP 200) menampilkan ringkasan data yang diinput | E5: Sesuai Harapan (Dashboard Admin termuat: True) | F5: Valid
A6: 2 | B6: Sistem menampilkan widget pemantauan dan persetujuan pada dashboard role Manager | C6: Buka URL '/dashboard' pada sesi role Manager | D6: Halaman dashboard menampilkan indikator data pending dan kontrol pengawasan | E6: Sesuai Harapan (Dashboard Manager termuat: True) | F6: Valid
A7: 3 | B7: Sistem menampilkan statistik bisnis komprehensif pada dashboard role Owner | C7: Buka URL '/dashboard' pada sesi role Owner | D7: Halaman dashboard menampilkan grafik/ringkasan performa seluruh modul bisnis | E7: Sesuai Harapan (Dashboard Owner termuat: True) | F7: Valid

Sheet Tender_Administrasi
A1: A. Pengujian Pada Modul Tender - Administrasi (Tender_Administrasi)
A2: Sistem Manajemen Operasional & Pelaporan PT Signal Panca Utama — Format Baku Pengujian Blackbox
A4: No | B4: Skenario Pengujian | C4: Test Case | D4: Hasil yang Diharapkan | E4: Hasil Pengujian | F4: Kesimpulan
A5: 1 | B5: Sistem dapat menampilkan daftar administrasi tender | C5: Kirim HTTP GET ke rute '/tender' | D5: Sistem merespons status HTTP 200 dan menyajikan tabel riwayat tender | E5: Sesuai Harapan (Status: 200) | F5: Valid
A6: 2 | B6: Sistem dapat mencatat data tender baru yang diajukan oleh Admin | C6: Admin mengisi form tender nama='Pengadaan Jaringan Fiber Optik Uji 1792233742', nilai='75000000', metode='internal' | D6: Tender tersimpan dengan status 'pending/draft' dan muncul pada daftar tender | E6: Sesuai Harapan (Status: 200) | F6: Valid
A7: 3 | B7: Sistem memvalidasi input wajib pada pembuatan tender saat form kosong | C7: Kirim POST '/tender' tanpa parameter data wajib (nama, nilai, metode) | D7: Sistem menolak penyimpanan dan mengembalikan error validasi | E7: Sesuai Harapan (Data kosong ditolak dan tidak disimpan) | F7: Valid
A8: 4 | B8: Sistem mewajibkan pengisian nama vendor relasi jika metode penanganan adalah subkontrak/vendor_relasi | C8: Input tender metode='vendor_relasi' dengan nama_vendor_relasi kosong | D8: Sistem memunculkan pesan error validasi bahwa nama vendor relasi wajib diisi | E8: Sesuai Harapan (Validasi menolak penyimpanan vendor relasi tanpa nama mitra) | F8: Valid
A9: 5 | B9: Sistem dapat melakukan pencarian data tender berdasarkan kata kunci | C9: Akses '/tender?search=Jaringan' | D9: Sistem merespons status 200 dan menampilkan hasil pencarian yang relevan | E9: Sesuai Harapan (Status: 200) | F9: Valid

Sheet Tender_RAB
A1: A. Pengujian Pada Modul Tender - Estimasi / RAB (Tender_RAB)
A2: Sistem Manajemen Operasional & Pelaporan PT Signal Panca Utama — Format Baku Pengujian Blackbox
A4: No | B4: Skenario Pengujian | C4: Test Case | D4: Hasil yang Diharapkan | E4: Hasil Pengujian | F4: Kesimpulan
A5: 1 | B5: Sistem dapat menampilkan daftar estimasi biaya dan RAB proyek tender | C5: Kirim HTTP GET ke rute '/tender/rab' | D5: Halaman modul RAB termuat sempurna (HTTP 200) menampilkan ringkasan rencana anggaran | E5: Sesuai Harapan (Status: 200) | F5: Valid
A6: 2 | B6: Sistem dapat menampilkan rincian rincian item pekerjaan dan material pada RAB | C6: Akses detail RAB '/tender/1/rab' | D6: Halaman rincian RAB termuat (HTTP 200) dengan rincian volume, satuan, dan harga | E6: Sesuai Harapan (Status HTTP: 200) | F6: Valid
A7: 3 | B7: Sistem memvalidasi nilai volume dan harga satuan tidak boleh negatif pada item RAB | C7: Input item RAB dengan volume='-5' dan harga_satuan='-100000' | D7: Sistem menolak input negatif dan tidak mengkalkulasi total anggaran negatif | E7: Sesuai Harapan (Sistem menolak nilai negatif melalui validasi server) | F7: Valid

Sheet Tender_Proyek
A1: A. Pengujian Pada Modul Tender - Proyek Lapangan (Tender_Proyek)
A2: Sistem Manajemen Operasional & Pelaporan PT Signal Panca Utama — Format Baku Pengujian Blackbox
A4: No | B4: Skenario Pengujian | C4: Test Case | D4: Hasil yang Diharapkan | E4: Hasil Pengujian | F4: Kesimpulan
A5: 1 | B5: Sistem dapat menampilkan daftar eksekusi proyek lapangan tender | C5: Kirim HTTP GET ke rute '/tender/proyek' | D5: Halaman proyek termuat (HTTP 200) menyajikan status pelaksanaan dan vendor | E5: Sesuai Harapan (Status: 200) | F5: Valid
A6: 2 | B6: Sistem menampilkan detail alokasi material, personil teknisi, dan log proyek | C6: Akses detail proyek '/tender/1/proyek' | D6: Detail proyek termuat (HTTP 200) dengan tab status, alokasi material, dan progres | E6: Sesuai Harapan (Status: 200) | F6: Valid
A7: 3 | B7: Sistem memvalidasi persentase progres vendor tidak boleh melebihi 100% | C7: Kirim pembaruan progres vendor dengan nilai '150%' | D7: Sistem menolak nilai di luar rentang 0-100% dan mengembalikan pesan validasi batas | E7: Sesuai Harapan (Input persentase di atas 100% ditolak validasi) | F7: Valid

Sheet Klien_Kontrak
A1: A. Pengujian Pada Modul Klien & Kontrak (Klien_Kontrak)
A2: Sistem Manajemen Operasional & Pelaporan PT Signal Panca Utama — Format Baku Pengujian Blackbox
A4: No | B4: Skenario Pengujian | C4: Test Case | D4: Hasil yang Diharapkan | E4: Hasil Pengujian | F4: Kesimpulan
A5: 1 | B5: Sistem dapat menampilkan daftar master klien / mitra perusahaan | C5: Akses URL '/clients' dengan sesi terautentikasi | D5: Tabel daftar klien termuat (HTTP 200) dengan data instansi, PIC, telepon, dan alamat | E5: Sesuai Harapan (Status HTTP: 200) | F5: Valid
A6: 2 | B6: Sistem dapat menambahkan data klien baru | C6: Input form klien nama='PT Sinergi Abadi 1792233754', telp='081234567890', alamat='Jakarta' | D6: Klien berhasil disimpan dan tercatat dalam database | E6: Sesuai Harapan (Status: 200) | F6: Valid
A7: 3 | B7: Sistem memvalidasi format email klien harus berformat alamat email yang benar | C7: Input data klien dengan email 'bukan_email_valid' | D7: Sistem menolak data dan menampilkan pesan error 'The email field must be a valid email address' | E7: Sesuai Harapan (Validasi format email bekerja dan menolak string tidak valid) | F7: Valid
A8: 4 | B8: Sistem dapat menampilkan daftar kontrak kerja dan status penandatanganan | C8: Kirim HTTP GET ke rute '/contracts' | D8: Halaman kontrak termuat (HTTP 200) dengan rincian nomor kontrak, nilai, dan masa berlaku | E8: Sesuai Harapan (Status: 200) | F8: Valid

Sheet Jasa_Pekerjaan
A1: A. Pengujian Pada Modul Jasa - Pekerjaan & Tagihan (Jasa_Pekerjaan)
A2: Sistem Manajemen Operasional & Pelaporan PT Signal Panca Utama — Format Baku Pengujian Blackbox
A4: No | B4: Skenario Pengujian | C4: Test Case | D4: Hasil yang Diharapkan | E4: Hasil Pengujian | F4: Kesimpulan
A5: 1 | B5: Sistem dapat menampilkan daftar pekerjaan operasional jasa layanan | C5: Kirim HTTP GET ke rute '/jasa' | D5: Halaman pekerjaan jasa termuat sempurna (HTTP 200) dengan tabel status pengerjaan | E5: Sesuai Harapan (Status: 200) | F5: Valid
A6: 2 | B6: Sistem dapat mencatat permohonan pekerjaan jasa baru oleh Admin | C6: Input pekerjaan jasa judul='Instalasi Access Point & Server 1792233762', tipe='installation', biaya='15000000' | D6: Pekerjaan jasa baru tersimpan dengan status 'pending' menunggu persetujuan Manager | E6: Sesuai Harapan (Status HTTP: 200) | F6: Valid
A7: 3 | B7: Sistem memvalidasi besaran biaya jasa tidak boleh bernilai negatif | C7: Input form jasa dengan nilai biaya '-5000000' | D7: Sistem menolak dan memunculkan error validasi angka minimal 0 | E7: Sesuai Harapan (Biaya negatif ditolak oleh validasi server) | F7: Valid

Sheet Jasa_Operasional
A1: A. Pengujian Pada Modul Jasa - Operasional & Teknisi (Jasa_Operasional)
A2: Sistem Manajemen Operasional & Pelaporan PT Signal Panca Utama — Format Baku Pengujian Blackbox
A4: No | B4: Skenario Pengujian | C4: Test Case | D4: Hasil yang Diharapkan | E4: Hasil Pengujian | F4: Kesimpulan
A5: 1 | B5: Sistem dapat menampilkan daftar teknisi dan status penugasan | C5: Akses URL '/jasa/teknisi' | D5: Halaman master teknisi termuat (HTTP 200) dengan data keahlian dan kontak | E5: Sesuai Harapan (Status: 200) | F5: Valid
A6: 2 | B6: Sistem dapat menyajikan halaman penanganan operasional instalasi | C6: Akses URL '/jasa/instalasi' | D6: Halaman instalasi terbuka (HTTP 200) dengan daftar tiket dan pekerjaan aktif | E6: Sesuai Harapan (Status: 200) | F6: Valid
A7: 3 | B7: Sistem dapat menyajikan halaman penanganan jadwal pemeliharaan / maintenance | C7: Akses URL '/jasa/maintenance' | D7: Halaman pemeliharaan terbuka (HTTP 200) dengan kontrol log berkala | E7: Sesuai Harapan (Status: 200) | F7: Valid

Sheet Supplier_Pengadaan
A1: A. Pengujian Pada Modul Supplier & Pengadaan (Supplier_Pengadaan)
A2: Sistem Manajemen Operasional & Pelaporan PT Signal Panca Utama — Format Baku Pengujian Blackbox
A4: No | B4: Skenario Pengujian | C4: Test Case | D4: Hasil yang Diharapkan | E4: Hasil Pengujian | F4: Kesimpulan
A5: 1 | B5: Sistem dapat menampilkan daftar mitra supplier / vendor penyedia barang | C5: Kirim HTTP GET ke rute '/suppliers' | D5: Daftar supplier termuat (HTTP 200) dengan data PIC dan nomor kontak | E5: Sesuai Harapan (Status: 200) | F5: Valid
A6: 2 | B6: Sistem dapat menambahkan data master supplier baru | C6: Input supplier nama='CV Mitra Mandiri Teknik 1792233771', PIC='Budi Santoso', submit form | D6: Data supplier baru tersimpan dalam database dengan status berhasil | E6: Sesuai Harapan (Status HTTP: 200) | F6: Valid
A7: 3 | B7: Sistem dapat menampilkan riwayat pengadaan barang (purchasing) | C7: Kirim HTTP GET ke rute '/procurements' | D7: Halaman pengadaan termuat (HTTP 200) dengan status pemesanan dan penerimaan | E7: Sesuai Harapan (Status: 200) | F7: Valid
A8: 4 | B8: Sistem memvalidasi pesanan pengadaan tidak boleh kosong tanpa item barang | C8: Kirim POST '/procurements' tanpa memilih item barang | D8: Sistem menolak penyimpanan pesanan pengadaan tanpa rincian item | E8: Sesuai Harapan (Validasi mencegah penyimpanan data pengadaan kosong) | F8: Valid

Sheet Produk_Gudang
A1: A. Pengujian Pada Modul Produk & Gudang (Produk_Gudang)
A2: Sistem Manajemen Operasional & Pelaporan PT Signal Panca Utama — Format Baku Pengujian Blackbox
A4: No | B4: Skenario Pengujian | C4: Test Case | D4: Hasil yang Diharapkan | E4: Hasil Pengujian | F4: Kesimpulan
A5: 1 | B5: Sistem dapat menampilkan katalog produk dan stok inventori gudang | C5: Kirim HTTP GET ke rute '/products' | D5: Katalog produk termuat (HTTP 200) menampilkan SKU/kode, nama produk, stok, dan harga | E5: Sesuai Harapan (Status: 200) | F5: Valid
A6: 2 | B6: Sistem dapat menambahkan master data produk baru | C6: Input produk kode='PRD-1792233777', nama='Switch Gigabit 24 Port', stok=25, harga jual=2300000 | D6: Produk baru tersimpan dan stok awal 25 unit tercatat dalam kartu stok | E6: Sesuai Harapan (Status HTTP: 200) | F6: Valid
A7: 3 | B7: Sistem menolak penambahan produk dengan kode/SKU yang sudah ada (duplikasi) | C7: Input ulang produk dengan kode yang sama persis ('PRD-1792233777') | D7: Sistem menolak dan menampilkan pesan error 'The code has already been taken' | E7: Sesuai Harapan (Validasi keunikan kode produk mencegah data ganda) | F7: Valid
A8: 4 | B8: Sistem dapat diakses melalui alias rute '/gudang' | C8: Akses URL '/gudang' | D8: Halaman inventori gudang terbuka sempurna (HTTP 200) | E8: Sesuai Harapan (Status HTTP: 200) | F8: Valid

Sheet Penjualan_Barang
A1: A. Pengujian Pada Modul Penjualan Barang (Penjualan_Barang)
A2: Sistem Manajemen Operasional & Pelaporan PT Signal Panca Utama — Format Baku Pengujian Blackbox
A4: No | B4: Skenario Pengujian | C4: Test Case | D4: Hasil yang Diharapkan | E4: Hasil Pengujian | F4: Kesimpulan
A5: 1 | B5: Sistem dapat menampilkan daftar riwayat transaksi penjualan barang | C5: Kirim HTTP GET ke rute '/sales' | D5: Halaman penjualan termuat (HTTP 200) menyajikan nomor transaksi, pembeli, total, dan status | E5: Sesuai Harapan (Status: 200) | F5: Valid
A6: 2 | B6: Sistem memvalidasi transaksi penjualan tidak boleh diproses tanpa memilih klien dan item produk | C6: Kirim POST '/sales' tanpa menyertakan parameter data barang | D6: Sistem menolak transaksi kosong dan memberikan notifikasi kesalahan | E6: Sesuai Harapan (Transaksi kosong ditolak oleh validasi sistem) | F6: Valid
A7: 3 | B7: Sistem dapat membuka modul penjualan melalui alias rute '/perdagangan' | C7: Kirim HTTP GET ke rute '/perdagangan' | D7: Halaman penjualan termuat (HTTP 200) | E7: Sesuai Harapan (Status: 200) | F7: Valid

Sheet Dokumen_Komersial
A1: A. Pengujian Pada Modul Dokumen Komersial (Dokumen_Komersial)
A2: Sistem Manajemen Operasional & Pelaporan PT Signal Panca Utama — Format Baku Pengujian Blackbox
A4: No | B4: Skenario Pengujian | C4: Test Case | D4: Hasil yang Diharapkan | E4: Hasil Pengujian | F4: Kesimpulan
A5: 1 | B5: Sistem dapat menampilkan daftar dokumen komersial (Quotation & Customer Order) | C5: Akses rute '/commercial-documents' | D5: Halaman dokumen komersial termuat (HTTP 200) dengan tab penawaran dan order | E5: Sesuai Harapan (Status: 200) | F5: Valid
A6: 2 | B6: Sistem memvalidasi field wajib pembuatan penawaran harga jasa (Service Quotation) | C6: Kirim form pembuatan Service Quotation tanpa data klien dan nilai penawaran | D6: Sistem mencegah pembuatan dokumen penawaran tanpa rincian valid | E6: Sesuai Harapan (Validasi menolak pengajuan penawaran kosong) | F6: Valid

Sheet Keuangan_Finance
A1: A. Pengujian Pada Modul Keuangan & Pembayaran (Keuangan_Finance)
A2: Sistem Manajemen Operasional & Pelaporan PT Signal Panca Utama — Format Baku Pengujian Blackbox
A4: No | B4: Skenario Pengujian | C4: Test Case | D4: Hasil yang Diharapkan | E4: Hasil Pengujian | F4: Kesimpulan
A5: 1 | B5: Sistem dapat menampilkan daftar tagihan / invoice keuangan | C5: Kirim HTTP GET ke rute '/finance' | D5: Halaman keuangan termuat (HTTP 200) dengan tabel nomor invoice, jatuh tempo, dan status lunas | E5: Sesuai Harapan (Status: 200) | F5: Valid
A6: 2 | B6: Sistem dapat menampilkan daftar riwayat pembayaran tagihan | C6: Kirim HTTP GET ke rute '/payments' | D6: Halaman pencatatan pembayaran termuat (HTTP 200) dengan histori bukti transfer | E6: Sesuai Harapan (Status: 200) | F6: Valid
A7: 3 | B7: Sistem memvalidasi nominal pembayaran tagihan tidak boleh bernilai negatif | C7: Kirim pencatatan pembayaran dengan nominal amount='-500000' | D7: Sistem menolak pembayaran dengan nominal kurang dari atau sama dengan 0 | E7: Sesuai Harapan (Validasi menolak pembayaran negatif) | F7: Valid

Sheet Laporan_Ekspor
A1: A. Pengujian Pada Modul Laporan & Ekspor (Laporan_Ekspor)
A2: Sistem Manajemen Operasional & Pelaporan PT Signal Panca Utama — Format Baku Pengujian Blackbox
A4: No | B4: Skenario Pengujian | C4: Test Case | D4: Hasil yang Diharapkan | E4: Hasil Pengujian | F4: Kesimpulan
A5: 1 | B5: Sistem dapat menampilkan dashboard laporan komprehensif seluruh domain bisnis | C5: Akses URL '/laporan' dengan akun Owner/Manager | D5: Halaman laporan termuat (HTTP 200) dengan filter domain, status, dan rentang tanggal | E5: Sesuai Harapan (Status: 200) | F5: Valid
A6: 2 | B6: Sistem dapat menyaring data laporan khusus domain Tender | C6: Pilih filter domain 'tender' pada halaman laporan | D6: Tabel laporan hanya menyajikan data transaksi dari domain tender | E6: Sesuai Harapan (Status: 200) | F6: Valid
A7: 3 | B7: Sistem dapat menyaring data laporan khusus domain Jasa | C7: Pilih filter domain 'jasa' pada halaman laporan | D7: Tabel laporan hanya menyajikan data transaksi dari domain pekerjaan jasa | E7: Sesuai Harapan (Status: 200) | F7: Valid
A8: 4 | B8: Sistem dapat menyaring data laporan khusus domain Perdagangan Barang | C8: Pilih filter domain 'barang' pada halaman laporan | D8: Tabel laporan menyajikan data transaksi barang secara spesifik | E8: Sesuai Harapan (Status: 200) | F8: Valid
A9: 5 | B9: Sistem dapat mengekspor rekapitulasi laporan ke format dokumen PDF | C9: Klik tombol 'Export PDF' atau akses URL '/laporan/export/pdf' | D9: Sistem mengunduh berkas berekstensi .pdf dengan tipe konten application/pdf | E9: Tidak Sesuai Harapan (Status: 200) | F9: Tidak Valid
A10: 6 | B10: Sistem dapat mengekspor rekapitulasi laporan ke format spreadsheet Excel (.xlsx) | C10: Klik tombol 'Export Excel' atau akses URL '/laporan/export/xlsx' | D10: Sistem mengunduh berkas Excel .xlsx dengan struktur tabel terformat | E10: Tidak Sesuai Harapan (Status: 200, Content-Type: 'text/html; charset=UTF-8' mengembalikan file CSV bertipe teks bukan format biner .xlsx) | F10: Tidak Valid

Sheet Admin_Sistem
A1: A. Pengujian Pada Administrasi Sistem & Keamanan (Admin_Sistem)
A2: Sistem Manajemen Operasional & Pelaporan PT Signal Panca Utama — Format Baku Pengujian Blackbox
A4: No | B4: Skenario Pengujian | C4: Test Case | D4: Hasil yang Diharapkan | E4: Hasil Pengujian | F4: Kesimpulan
A5: 1 | B5: Sistem menyediakan audit trail aktivitas pengguna pada halaman Log Aktivitas | C5: Akses rute '/activity-logs' dengan akun Owner | D5: Log aktivitas pengguna termuat (HTTP 200) mencatat user, modul, aksi, dan waktu | E5: Sesuai Harapan (Status HTTP: 200) | F5: Valid
A6: 2 | B6: Sistem membatasi hak akses audit log sehingga role Admin tidak dapat melihatnya | C6: Kirim HTTP GET ke '/activity-logs' pada sesi role Admin | D6: Sistem menolak akses dengan HTTP 403 Forbidden atau redirect dengan pesan error hak akses | E6: Sesuai Harapan (Status: 302, Akses dicegah) | F6: Valid
A7: 3 | B7: Sistem mengizinkan role Owner mengelola akun pengguna (User Management) | C7: Akses rute '/users' dengan sesi akun Owner | D7: Halaman manajemen pengguna terbuka (HTTP 200) dengan daftar user dan tombol aksi | E7: Sesuai Harapan (Status: 200) | F7: Valid
A8: 4 | B8: Sistem melarang role Manager mengakses halaman manajemen pengguna | C8: Kirim HTTP GET ke '/users' pada sesi role Manager | D8: Sistem menolak dengan HTTP 403 Forbidden atau redirect pencegahan | E8: Sesuai Harapan (Status: 302, Akses dicegah) | F8: Valid
A9: 5 | B9: Sistem menyajikan matriks permission role pada rute '/permissions' | C9: Akses URL '/permissions' pada sesi role Owner | D9: Halaman matriks izin terbuka (HTTP 200) dengan checkbox permission per role | E9: Sesuai Harapan (Status: 200) | F9: Valid
A10: 6 | B10: Sistem memvalidasi token CSRF pada seluruh request mutasi data (POST) | C10: Kirim request POST ke '/tender' tanpa menyertakan token '_token' / header CSRF | D10: Sistem menolak dengan status HTTP 419 Page Expired / CSRF Token Mismatch | E10: Sesuai Harapan (Status: 419 Page Expired) | F10: Valid
A11: 7 | B11: Sistem kebal terhadap serangan dasar SQL Injection pada input parameter query | C11: Kirim query pencarian dengan payload SQLi '' OR '1'='1' -- ' | D11: Sistem menangani input secara aman via parameterized query tanpa kebocoran sintaks SQL | E11: Sesuai Harapan (Tidak ada syntax error SQL atau data dump tak terkontrol) | F11: Valid
A12: 8 | B12: Sistem melakukan escaping pada karakter tag HTML untuk mencegah Cross-Site Scripting (XSS) | C12: Input nama klien berisi payload '<script>alert('XSS_TEST')</script>' dan periksa output pada tabel | D12: Sistem melakukan sanitasi/HTML entity encode sehingga skrip tidak dapat dieksekusi | E12: Sesuai Harapan (Karakter HTML di-escape secara otomatis oleh template engine Blade) | F12: Valid

Sheet Daftar Bug
A1: DAFTAR TEMUAN BUG & ANOMALI SISTEM
A2: Hasil Eksekusi Blackbox Testing — Tanpa Mengubah Kode Sumber Aplikasi
A4: ID | B4: Modul | C4: Judul Bug / Anomali | D4: Severity | E4: Langkah Reproduksi | F4: Expected | G4: Actual | H4: Bukti (Evidence) | I4: Referensi No Test Case
A5: BUG-01 | B5: Laporan_Ekspor | C5: Endpoint Export Excel (/laporan/export/xlsx) Mengembalikan Konten Teks CSV Bukan Format Spreadsheet Biner OpenXML (.xlsx) | D5: Medium | E5: 1. Login sebagai akun Owner / Manager 2. Masuk ke menu Laporan (/laporan) 3. Klik tombol 'Export Excel' atau akses URL '/laporan/export/xlsx' 4. Periksa header 'Content-Type' dan konten berkas yang terunduh | F5: Sistem menghasilkan file spreadsheet Excel biner berekstensi .xlsx dengan Content-Type 'application/vnd.openxmlformats-officedocument.spreadsheetml.sheet' | G5: Sistem mengembalikan file dengan Content-Type 'text/csv; charset=UTF-8' berisi data berformat plain-text CSV (comma separated values) | H5: laporan_index.png | I5: Laporan_Ekspor No. 6
A6: BUG-02 | B6: Admin_Sistem | C6: Ketiadaan Header Keamanan HTTP Standar (X-Frame-Options, X-Content-Type-Options, CSP, HSTS) pada Respons Server | D6: Low | E6: 1. Kirim HTTP GET request ke root web '/' atau '/login' 2. Periksa response headers yang dikirim oleh aplikasi web | F6: Respons web menyertakan header proteksi keamanan standar seperti 'X-Frame-Options: SAMEORIGIN', 'X-Content-Type-Options: nosniff', dan 'Content-Security-Policy' | G6: Seluruh header keamanan tersebut tidak ditemukan (Missing) pada respons web server, meningkatkan risiko clickjacking jika di-embed dalam iframe | H6: home_desktop.png | I6: Admin_Sistem No. 6
A7: BUG-03 | B7: Beranda | C7: Margin dan Padding Komponen Mepet Tepi Layar pada Tampilan Mobile Resolusi 375px | D7: Low | E7: 1. Buka landing page pada resolusi viewport mobile (375x812 px) 2. Periksa section logo mitra dan kartu ulasan layanan | F7: Terdapat padding horizontal pengaman minimal 12-16px di sisi kiri dan kanan layar untuk kenyamanan sentuhan dan keterbacaan | G7: Beberapa badge dan container kartu mepet langsung ke tepi layar (< 6px), mengurangi estetika tata letak responsif | H7: home_mobile.png | I7: Beranda No. 2

Sheet Performa & Keamanan
A1: HASIL UJI PERFORMA, KEAMANAN, DAN AKSESIBILITAS
A2: Metrik Kuantitatif Waktu Respons, Daya Tahan Konkurensi, Audit Keamanan HTTP, dan WCAG
A4: 1. HASIL UJI WAKTU RESPONS (LATENSI HTTP PER ENDPOINT)
A5: No | B5: Endpoint URL | C5: HTTP Status | D5: Min Latensi (ms) | E5: Max Latensi (ms) | F5: Rata-rata (ms) | G5: Standar Evaluasi
A6: 1 | B6: / | C6: 200 | D6: 299.2 | E6: 353.4 | F6: 322.9 | G6: Sangat Cepat (< 500 ms)
A7: 2 | B7: /login | C7: 200 | D7: 277.9 | E7: 407.7 | F7: 333.8 | G7: Sangat Cepat (< 500 ms)
A8: 3 | B8: /dashboard | C8: 200 | D8: 495.5 | E8: 654.8 | F8: 552.7 | G8: Baik (< 1000 ms)
A9: 4 | B9: /tender | C9: 200 | D9: 417.7 | E9: 530.1 | F9: 462.7 | G9: Sangat Cepat (< 500 ms)
A10: 5 | B10: /jasa | C10: 200 | D10: 373.7 | E10: 490.3 | F10: 438.3 | G10: Sangat Cepat (< 500 ms)
A11: 6 | B11: /products | C11: 200 | D11: 432.4 | E11: 649.7 | F11: 571.3 | G11: Baik (< 1000 ms)
A12: 7 | B12: /sales | C12: 200 | D12: 436.2 | E12: 629.3 | F12: 544.2 | G12: Baik (< 1000 ms)
A13: 8 | B13: /finance | C13: 200 | D13: 332.4 | E13: 520 | F13: 439.1 | G13: Sangat Cepat (< 500 ms)
A14: 9 | B14: /laporan | C14: 200 | D14: 401.2 | E14: 454.9 | F14: 434.9 | G14: Sangat Cepat (< 500 ms)
A17: 2. HASIL UJI BEBAN KONKURENSI (STRESS TEST RINGAN)
A18: Parameter Uji | B18: Hasil Pengukuran Kinerja
A19: Total Permintaan Simultan | B19: 20 Requests
A20: Jumlah Worker Paralel | B20: 5 Threads Konkuren
A21: Tingkat Keberhasilan (Success Rate) | B21: 100.0% (200 OK)
A22: Throughput (RPS) | B22: 1.97 Req/Sec
A23: Rata-rata Waktu Respons | B23: 2291.5 ms
A24: Rentang Waktu Latensi | B24: 514.5 ms - 2861.1 ms
A25: Ketahanan Server | B25: STABIL — Tidak ada crash atau thread leak pada server internal
A28: 3. AUDIT KEAMANAN HTTP & HEADER PERLINDUNGAN
A29: No | B29: Nama Security Header | C29: Fungsi Perlindungan | D29: Nilai Terdeteksi | E29: Status Keamanan
A30: 1 | B30: X-Frame-Options | C30: SAMEORIGIN / DENY (Clickjacking protection) | D30: Tidak Ditemukan (Missing) | E30: Rekomendasi Penambahan
A31: 2 | B31: X-Content-Type-Options | C31: nosniff (MIME-sniffing protection) | D31: Tidak Ditemukan (Missing) | E31: Rekomendasi Penambahan
A32: 3 | B32: X-XSS-Protection | C32: 1; mode=block (XSS filter) | D32: Tidak Ditemukan (Missing) | E32: Rekomendasi Penambahan
A33: 4 | B33: Strict-Transport-Security | C33: max-age=... (HSTS) | D33: Tidak Ditemukan (Missing) | E33: Rekomendasi Penambahan
A34: 5 | B34: Content-Security-Policy | C34: CSP directives | D34: Tidak Ditemukan (Missing) | E34: Rekomendasi Penambahan
A35: 6 | B35: Referrer-Policy | C35: no-referrer-when-downgrade / strict-origin | D35: Tidak Ditemukan (Missing) | E35: Rekomendasi Penambahan
A38: 4. AUDIT PROTEKSI SERANGAN & AKSESIBILITAS WEB
A39: Proteksi Brute Force Login | B39: throttle:5,1 (Maksimal 5 percobaan per menit) — Aktif (Mengembalikan HTTP 429 Too Many Requests)
A40: Proteksi Token CSRF | B40: AKTIF (HTTP 419 Token Mismatch pada request tanpa token)
A41: Proteksi SQL Injection | B41: AMAN (Eloquent ORM Parameterized Query mencegah payload sql injection)
A42: Proteksi XSS | B42: AMAN (Blade automatic escaping pada kurung kurawal ganda {{ $var }})
A43: Kelengkapan Alt Gambar | B43: 21 dari 21 gambar memiliki atribut alt (100.0%)
A44: Label Elemen Form Login | B44: 5 dari 5 kontrol input memiliki label/aria-label eksplisit
A45: Hierarki Heading Semantik | B45: H1: 1 elemen, H2: 3 elemen (Struktur SEO & Aksesibilitas Valid)

Sheet Tidak Teruji
A1: DAFTAR AREA FITUR YANG TIDAK DAPAT DIUJI (BLOCKED / OUT OF SCOPE)
A2: Dokumentasi Hambatan & Justifikasi Teknis Berdasarkan Lingkungan Lokal
A4: No | B4: Nama Fitur / Modul | C4: Kategori Hambatan | D4: Alasan Teknis Tidak Dapat Diuji | E4: Dampak Terhadap Sistem | F4: Status Rekomendasi
A5: 1 | B5: Single Sign-On (SSO) OAuth Google (/auth/google/redirect) | C5: Third-Party Credentials | D5: Membutuhkan Google Client ID dan Client Secret resmi yang aktif dan terdaftar di Google Cloud Console dengan domain publik callback yang valid. File .env lokal saat ini belum memiliki kredensial tersebut. | E5: Pengguna tidak dapat menguji login instan via akun Google Gmail pada server pengujian lokal. | F5: Blocked (Perlu konfigurasi API Console)
A6: 2 | B6: Single Sign-On (SSO) OAuth LinkedIn (/auth/linkedin/redirect) | C6: Third-Party Credentials | D6: Membutuhkan LinkedIn Client ID dan Client Secret yang telah diapprove pada LinkedIn Developer Platform. File konfigurasi lokal (.env) masih berisi string kosong. | E6: Pengguna tidak dapat login menggunakan akun profesional LinkedIn pada server pengujian lokal. | F6: Blocked (Perlu verifikasi App LinkedIn)
A7: 3 | B7: Pengiriman Email Nyata Pemulihan Password (Live SMTP) | C7: Testing Safety Rules (#5) | D7: Sesuai Aturan Ketat Pengujian #5: 'DILARANG mengirim email/SMS/pembayaran sungguhan'. Server lokal menggunakan Mailpit/Log driver sehingga surat elektronik tidak dihantarkan ke server email penerima publik. | E7: Tidak ada email sungguhan yang masuk ke inbox pengguna luar; pengujian dibatasi pada verifikasi form dan token reset. | F7: Aman & Terisolasi (Sesuai Aturan QA)
A8: 4 | B8: Payment Gateway Otomatis (Live Bank / Virtual Account) | C8: Business Architecture Scope | D8: Sesuai PRD, pencatatan pembayaran keuangan sistem PT Signal Panca Utama menggunakan mekanisme konfirmasi internal (Manual Bank Transfer Verification) dan belum mengintegrasikan webhook gateway pihak ketiga. | E8: Verifikasi pembayaran dilakukan secara manual oleh staff admin/finance melalui form input pembayaran. | F8: By Design (Sesuai Spesifikasi PRD)
